openevse.py
python_openevse-0.6.dist-info/DESCRIPTION.rst
python_openevse-0.6.dist-info/METADATA
python_openevse-0.6.dist-info/RECORD
python_openevse-0.6.dist-info/WHEEL
python_openevse-0.6.dist-info/metadata.json
python_openevse-0.6.dist-info/top_level.txt
