Metadata-Version: 2.0
Name: python-openevse
Version: 0.6
Summary: Control OpenEVSE boards
Home-page: https://github.com/tiramiseb/python-openevse
Author: Sébastien Maccagnoni-Munch
Author-email: seb+pythonopenevse@maccagnoni.eu
License: MIT
Keywords: openevse serial rapi
Platform: UNKNOWN
Classifier: Development Status :: 3 - Alpha
Classifier: Intended Audience :: Developers
Classifier: License :: OSI Approved :: MIT License
Classifier: Programming Language :: Python :: 3
Classifier: Programming Language :: Python :: 3.5
Classifier: Programming Language :: Python :: 3.6
Requires-Dist: pyserial
